nettacker/__init__.py
nettacker/api/__init__.py
nettacker/api/api_core.py
nettacker/api/database.sqlite3
nettacker/api/engine.py
nettacker/api/readme.md
nettacker/api/run.py
nettacker/config.py
nettacker/core/__init__.py
nettacker/core/alert.py
nettacker/core/args_loader.py
nettacker/core/color.py
nettacker/core/compatible.py
nettacker/core/die.py
nettacker/core/graph.py
nettacker/core/ip.py
nettacker/core/load_modules.py
nettacker/core/messages.py
nettacker/core/module_protocols/__init__.py
nettacker/core/module_protocols/core_ftp.py
nettacker/core/module_protocols/core_http.py
nettacker/core/module_protocols/core_pop3.py
nettacker/core/module_protocols/core_smtp.py
nettacker/core/module_protocols/core_socket.py
nettacker/core/module_protocols/core_ssh.py
nettacker/core/module_protocols/core_telnet.py
nettacker/core/parse.py
nettacker/core/readme.md
nettacker/core/scan_targets.py
nettacker/core/socks_proxy.py
nettacker/core/targets.py
nettacker/core/time.py
nettacker/core/utility.py
nettacker/database/__init__.py
nettacker/database/db.py
nettacker/database/models.py
nettacker/database/mysql_create.py
nettacker/database/postgres_create.py
nettacker/database/readme.md
nettacker/database/sqlite_create.py
nettacker/lib/__init__.py
nettacker/lib/graph/__init__.py
nettacker/lib/graph/d3_tree_v1/__init__.py
nettacker/lib/graph/d3_tree_v1/engine.py
nettacker/lib/graph/d3_tree_v1/readme.md
nettacker/lib/graph/d3_tree_v2/__init__.py
nettacker/lib/graph/d3_tree_v2/engine.py
nettacker/lib/graph/d3_tree_v2/readme.md
nettacker/lib/graph/readme.md
nettacker/lib/html_log/__init__.py
nettacker/lib/html_log/log_data.py
nettacker/lib/html_log/readme.md
nettacker/lib/icmp/__init__.py
nettacker/lib/icmp/engine.py
nettacker/lib/icmp/readme.md
nettacker/lib/messages/ar.yaml
nettacker/lib/messages/bn.yaml
nettacker/lib/messages/de.yaml
nettacker/lib/messages/el.yaml
nettacker/lib/messages/en.yaml
nettacker/lib/messages/es.yaml
nettacker/lib/messages/fa.yaml
nettacker/lib/messages/fr.yaml
nettacker-0.3.1a17.dist-info/LICENSE
nettacker-0.3.1a17.dist-info/METADATA
nettacker-0.3.1a17.dist-info/WHEEL
nettacker-0.3.1a17.dist-info/RECORD
