Metadata-Version: 2.1
Name: nettacker
Version: 0.3.1a17
Summary: Automates information gathering, vulnerability scanning and aids penetration testing engagements in general
Home-page: https://owasp.org/www-project-nettacker
License: Apache-2.0
Keywords: automation,bruteforce,cve,hacking-tools,information-gathering,network-analysis,owasp,penetration-testing,pentesting,pentesting-tools,port-scanner,python,security-tools,security,vulnerability-management,vulnerability-scanner
Author: OWASP Nettacker Contributors
Requires-Python: >=3.9,<3.13
Classifier: License :: OSI Approved :: Apache Software License
Classifier: Operating System :: OS Independent
Classifier: Programming Language :: Python :: 3
Classifier: Programming Language :: Python :: 3.9
Classifier: Programming Language :: Python :: 3.10
Classifier: Programming Language :: Python :: 3.11
Requires-Dist: aiohttp (>=3.8.6,<4.0.0)
Requires-Dist: argparse (>=1.4.0,<2.0.0)
Requires-Dist: asyncio (>=3.4.3,<4.0.0)
Requires-Dist: flask (>=3.0.0,<4.0.0)
Requires-Dist: ipaddr (>=2.2.0,<3.0.0)
Requires-Dist: netaddr (>=0.9.0,<0.10.0)
Requires-Dist: numpy (>=1.26.1,<2.0.0)
Requires-Dist: paramiko (>=3.3.1,<4.0.0)
Requires-Dist: py3dns (>=4.0.0,<5.0.0)
Requires-Dist: pyopenssl (>=23.2.0,<24.0.0)
Requires-Dist: pysocks (>=1.7.1,<2.0.0)
Requires-Dist: pyyaml (>=6.0.1,<7.0.0)
Requires-Dist: requests (>=2.31.0,<3.0.0)
Requires-Dist: sqlalchemy (>=2.0.22,<3.0.0)
Requires-Dist: terminable-thread (>=0.7.1,<0.8.0)
Requires-Dist: texttable (>=1.7.0,<2.0.0)
Project-URL: Documentation, https://github.com/OWASP/Nettacker/wiki
Project-URL: Repository, https://github.com/OWASP/Nettacker
Project-URL: Sponsor, https://owasp.org/donate/?reponame=www-project-nettacker&title=OWASP+Nettacker
